[{"__symbolic":"module","version":4,"metadata":{"FileNode":{"__symbolic":"class"},"FileFlatNode":{"__symbolic":"class","members":{"__ctor__":[{"__symbolic":"constructor","parameters":[{"__symbolic":"reference","name":"boolean"},{"__symbolic":"reference","name":"string"},{"__symbolic":"reference","name":"number"},{"__symbolic":"reference","name":"any"}]}]}},"FileDatabase":{"__symbolic":"class","decorators":[{"__symbolic":"call","expression":{"__symbolic":"reference","module":"@angular/core","name":"Injectable","line":67,"character":1}}],"members":{"__ctor__":[{"__symbolic":"constructor"}],"initialize":[{"__symbolic":"method"}],"buildFileTree":[{"__symbolic":"method"}]}},"CdkTreeFlatExample":{"__symbolic":"class","decorators":[{"__symbolic":"call","expression":{"__symbolic":"reference","module":"@angular/core","name":"Component","line":115,"character":1},"arguments":[{"selector":"cdk-tree-flat-example","templateUrl":"cdk-tree-flat-example.html","styleUrls":["cdk-tree-flat-example.css"],"providers":[{"__symbolic":"reference","name":"FileDatabase"}]}]}],"members":{"__ctor__":[{"__symbolic":"constructor","parameters":[{"__symbolic":"reference","name":"FileDatabase"}]}]}}}}]